beijing_fushengji/__main__.py
beijing_fushengji/help_en_html.py
beijing_fushengji/help_html.py
beijing_fushengji/main_rc.py
beijing_fushengji/app/defs.py
beijing_fushengji/app/events.py
beijing_fushengji/app/main.py
beijing_fushengji/app/models.py
beijing_fushengji/app/tools.py
beijing_fushengji/console/mainwindow.py
beijing_fushengji/ui/about.py
beijing_fushengji/ui/airport.py
beijing_fushengji/ui/bank.py
beijing_fushengji/ui/beijing_intro.py
beijing_fushengji/ui/buy.py
beijing_fushengji/ui/celebrate.py
beijing_fushengji/ui/diary.py
beijing_fushengji/ui/easteregg.py
beijing_fushengji/ui/hospital.py
beijing_fushengji/ui/main_widget.py
beijing_fushengji/ui/mainwindow.py
beijing_fushengji/ui/money_exchange.py
beijing_fushengji/ui/net_cafe.py
beijing_fushengji/ui/news.py
beijing_fushengji/ui/pay_debt.py
beijing_fushengji/ui/rent.py
beijing_fushengji/ui/sell.py
beijing_fushengji/ui/send_money.py
beijing_fushengji/ui/settings.py
beijing_fushengji/ui/statements.py
beijing_fushengji/ui/story.py
beijing_fushengji/ui/text_editor.py
beijing_fushengji/ui/top_players.py
beijing_fushengji/widgets/about.py
beijing_fushengji/widgets/bank.py
beijing_fushengji/widgets/buy.py
beijing_fushengji/widgets/debug_window.py
beijing_fushengji/widgets/hospital.py
beijing_fushengji/widgets/main_widget.py
beijing_fushengji/widgets/mainwindow.py
beijing_fushengji/widgets/my_table_model.py
beijing_fushengji/widgets/pay_debt.py
beijing_fushengji/widgets/simple_dialogs.py
beijing_fushengji/widgets/story.py
beijing_fushengji/widgets/styled_widget.py
beijing_fushengji/widgets/tables.py
beijing_fushengji/widgets/top_players.py
beijing_fushengji-2025.1.21.0.dist-info/METADATA
beijing_fushengji-2025.1.21.0.dist-info/WHEEL
beijing_fushengji-2025.1.21.0.dist-info/entry_points.txt
beijing_fushengji-2025.1.21.0.dist-info/licenses/LICENSE
beijing_fushengji-2025.1.21.0.dist-info/RECORD
