Metadata-Version: 2.4
Name: beijing_fushengji
Version: 2025.1.21.0
Summary: beijing fushengji (a simple simulation game) rewritten in Python
Project-URL: Repository, https://github.com/soda92/beijing_fushengji_rewrite.git
License-File: LICENSE
Classifier: Topic :: Games/Entertainment :: Turn Based Strategy
Requires-Python: >=3.12
Requires-Dist: pyside6>=6.6.3.1
